guineapig/__init__.py
guineapig/main.py
guineapig/prompt.py
guineapig/utils.py
guineapig-0.3.0.dist-info/LICENSE.txt
guineapig-0.3.0.dist-info/METADATA
guineapig-0.3.0.dist-info/WHEEL
guineapig-0.3.0.dist-info/entry_points.txt
guineapig-0.3.0.dist-info/top_level.txt
guineapig-0.3.0.dist-info/RECORD
