Metadata-Version: 2.1
Name: guineapig
Version: 0.3.0
Summary: CLI for tracking pocket money
Home-page: https://github.com/bichanna/guineapig
Author: bichanna
Author-email: nobu.bichanna@gmail.com
License: MIT
Keywords: guineapig,python
Platform: UNKNOWN
Classifier: Environment :: Console
Classifier: Development Status :: 4 - Beta
Requires-Dist: click
Requires-Dist: mysql-connector-python
Requires-Dist: protobuf
Requires-Dist: six
